Workbook

Sheet Expense Report
A1: Date | B1: Vendor / Merchant | C1: Description | D1: Attendees (if Applicable) | E1: GL Account | F1: Amount | G1: Do you have a reciept? | H1: Is this tied to a specific PO/SO? What number? | I1: Notes | M1: Name | N1: Greg Morris
E2: 6100 – Rent / Utilities | M2: Date | N2: 46197
E3: 6700 – Software / Subscriptions | M3: Total Owed | N3: =+SUM(F2:F29)+Mileage!D33 -> 0
E4: 6230 – Office Supplies
E5: 6230 – Office Supplies

Sheet Mileage
A1: Day | B1: Mileage Total | C1: Comments
A2: 1
A3: 2
A4: 3
A5: 4
A6: 5
A7: 6
A8: 7
A9: 8
A10: 9
A11: 10
A12: 11
A13: 12
... A32: 31
B33: =SUM(B2:B32) -> 0 | C33: 0.7 | D33: =C33*B33 -> 0

Sheet Account Listing
A1: Account Number | B1: Account Name | C1: GL (Number - Name)
A2: 1250 | B2: Packaging Inventory | C2: 1250 - Packaging Inventory | D2: =SUMIFS('Expense Report'!F:F,'Expense Report'!E:E,'Account Listing'!C2) -> 0
A3: 1300 | B3: Land Cost Account | C3: 1300- Landed Cost Account | D3: =SUMIFS('Expense Report'!F:F,'Expense Report'!E:E,'Account Listing'!C3) -> 0
A4: 6210 | B4: Lab Supplies | C4: 6210 - Lab Supplies | D4: =SUMIFS('Expense Report'!F:F,'Expense Report'!E:E,'Account Listing'!C4) -> 0
A5: 6220 | B5: Production Supplies | C5: 6220 - Production Supplies | D5: =SUMIFS('Expense Report'!F:F,'Expense Report'!E:E,'Account Listing'!C5) -> 0
A6: 6230 | B6: Office Supplies | C6: 6230 – Office Supplies | D6: =SUMIFS('Expense Report'!F:F,'Expense Report'!E:E,'Account Listing'!C6) -> 0
A7: 5000 | B7: Raw Materials Used | C7: 5000 – Raw Materials Used | D7: =SUMIFS('Expense Report'!F:F,'Expense Report'!E:E,'Account Listing'!C7) -> 0
A8: 5100 | B8: Freight-in / Import Freight | C8: 5100 – Freight-in / Import Freight | D8: =SUMIFS('Expense Report'!F:F,'Expense Report'!E:E,'Account Listing'!C8) -> 0
A9: 5200 | B9: Customs, Duties & Tariffs | C9: 5200 – Customs, Duties & Tariffs | D9: =SUMIFS('Expense Report'!F:F,'Expense Report'!E:E,'Account Listing'!C9) -> 0
A10: 5400 | B10: Packaging Supplies | C10: 5400 – Packaging Supplies | D10: =SUMIFS('Expense Report'!F:F,'Expense Report'!E:E,'Account Listing'!C10) -> 0
A11: 5500 | B11: Subcontract / Blending Labor | C11: 5500 – Subcontract / Blending Labor | D11: =SUMIFS('Expense Report'!F:F,'Expense Report'!E:E,'Account Listing'!C11) -> 0
A12: 6010 | B12: Payroll Taxes | C12: 6010 – Payroll Taxes | D12: =SUMIFS('Expense Report'!F:F,'Expense Report'!E:E,'Account Listing'!C12) -> 0
A13: 6020 | B13: Wages | C13: 6020 – Wages | D13: =SUMIFS('Expense Report'!F:F,'Expense Report'!E:E,'Account Listing'!C13) -> 0
A14: 6050 | B14: Employee Events & Recognition | C14: 6050 – Employee Events & Recognition | D14: =SUMIFS('Expense Report'!F:F,'Expense Report'!E:E,'Account Listing'!C14) -> 0
A15: 6100 | B15: Rent / Utilities | C15: 6100 – Rent / Utilities | D15: =SUMIFS('Expense Report'!F:F,'Expense Report'!E:E,'Account Listing'!C15) -> 0
A16: 6300 | B16: Professional Fees | C16: 6300 – Professional Fees | D16: =SUMIFS('Expense Report'!F:F,'Expense Report'!E:E,'Account Listing'!C16) -> 0
A17: 6410 | B17: Travel Expense | C17: 6410 – Travel Expense | D17: =SUMIFS('Expense Report'!F:F,'Expense Report'!E:E,'Account Listing'!C17) -> 0
A18: 6415 | B18: Travel – Employee Meals (50% deductible) | C18: 6415 – Travel – Employee Meals (50% deductible) | D18: =SUMIFS('Expense Report'!F:F,'Expense Report'!E:E,'Account Listing'!C18) -> 0
... A36: 7140 | B36: Regulatory Filings & Permits | C36: 7140 – Regulatory Filings & Permits | D36: =SUMIFS('Expense Report'!F:F,'Expense Report'!E:E,'Account Listing'!C36) -> 0
D37: =SUM(D2:D36) -> 0
